fiximport/__init__.py
fiximport/fiximport.py
fiximport-1.0.3.dist-info/LICENSE
fiximport-1.0.3.dist-info/METADATA
fiximport-1.0.3.dist-info/WHEEL
fiximport-1.0.3.dist-info/top_level.txt
fiximport-1.0.3.dist-info/RECORD
