Metadata-Version: 2.1
Name: fiximport
Version: 1.0.3
Summary: Fixes `ModuleNotFoundError` exceptions
Home-page: https://github.com/ELanning/fiximport
Author: Erik Lanning
Author-email: cs@eriklanning.com
Project-URL: Documentation, https://github.com/ELanning/fiximport
Project-URL: Bug Reports, https://github.com/ELanning/fiximport/issues
Project-URL: Source Code, https://github.com/ELanning/fiximport
Keywords: ModuleNotFoundError,absolute import,fix imports
Classifier: Development Status :: 5 - Production/Stable
Classifier: Intended Audience :: Developers
Classifier: Topic :: Software Development :: Libraries :: Python Modules
Classifier: Programming Language :: Python :: 3
Classifier: Programming Language :: Python :: 3.6
Classifier: Programming Language :: Python :: 3.7
Classifier: Programming Language :: Python :: 3.8
Classifier: Programming Language :: Python :: 3.9
Classifier: Programming Language :: Python :: 3 :: Only
Classifier: License :: OSI Approved :: MIT License
Classifier: Operating System :: OS Independent
Requires-Python: >=3.6
License-File: LICENSE
Provides-Extra: dev
Requires-Dist: check-manifest ; extra == 'dev'
